gmk_utils/__init__.py
gmk_utils/functions.py
gmk_utils-0.1.1.data/data/gmk_utils/solrs/solr-8.9.0.zip
gmk_utils-0.1.1.dist-info/LICENSE
gmk_utils-0.1.1.dist-info/METADATA
gmk_utils-0.1.1.dist-info/WHEEL
gmk_utils-0.1.1.dist-info/top_level.txt
gmk_utils-0.1.1.dist-info/RECORD
