Metadata-Version: 2.2
Name: gmk_utils
Version: 0.1.1
Home-page: https://github.com/gmk-dev/gmk_utils
License: MIT
License-File: LICENSE
Requires-Dist: numpy>=1.21.0
Dynamic: description
Dynamic: description-content-type
Dynamic: home-page
Dynamic: license
Dynamic: requires-dist
